AutoNN/__init__.py
AutoNN/_main_.py
AutoNN/default_config.json
AutoNN/exceptions.py
AutoNN/main.py
AutoNN/CNN/__init__.py
AutoNN/CNN/autoEDs.py
AutoNN/CNN/cnnBlocks.py
AutoNN/CNN/cnn_generator.py
AutoNN/CNN/models/__init__.py
AutoNN/CNN/models/resnet.py
AutoNN/CNN/models/smolnets.py
AutoNN/CNN/utils/Device.py
AutoNN/CNN/utils/EDA.py
AutoNN/CNN/utils/__init__.py
AutoNN/CNN/utils/image_augmentation.py
AutoNN/networkbuilding/__init__.py
AutoNN/networkbuilding/basic_data_cleaning.py
AutoNN/networkbuilding/dataframe_extractor.py
AutoNN/networkbuilding/dropout_optimization.py
AutoNN/networkbuilding/final.py
AutoNN/networkbuilding/hyperparameter_optimization.py
AutoNN/networkbuilding/model_gen_train_test.py
AutoNN/networkbuilding/model_generation.py
AutoNN/networkbuilding/model_optimization.py
AutoNN/networkbuilding/model_stacking.py
AutoNN/networkbuilding/multiple_model_gen_v1.py
AutoNN/networkbuilding/multiple_model_gen_v2.py
AutoNN/networkbuilding/multiple_model_gen_v3.py
AutoNN/networkbuilding/search_space_gen_v1.py
AutoNN/networkbuilding/utilities.py
AutoNN/preprocessing/__init__.py
AutoNN/preprocessing/column_info.py
AutoNN/preprocessing/data_cleaning.py
AutoNN/preprocessing/dataset_container.py
AutoNN/preprocessing/date_parsing.py
AutoNN/preprocessing/encoding.py
AutoNN/preprocessing/encoding_v2.py
AutoNN/preprocessing/encoding_v3.py
AutoNN/preprocessing/feature_elimination.py
AutoNN/preprocessing/nan_handling.py
nocode_autonn-2.4.1.dist-info/METADATA
nocode_autonn-2.4.1.dist-info/WHEEL
nocode_autonn-2.4.1.dist-info/entry_points.txt
nocode_autonn-2.4.1.dist-info/top_level.txt
nocode_autonn-2.4.1.dist-info/RECORD
