Metadata-Version: 2.1
Name: nocode-autonn
Version: 2.4.1
Summary: An AutoML framework for deep learning
Home-page: https://github.com/AutoNN/AutoNN
Author-email: raju.banerjee.720@gmail.com
License: Apache License 2.0
Keywords: AutoNN,autonn,AutoML,Deep Learning,CNN
Classifier: Intended Audience :: Developers
Classifier: Intended Audience :: Education
Classifier: Intended Audience :: Science/Research
Classifier: License :: OSI Approved :: Apache Software License
Classifier: Programming Language :: Python :: 3.8
Classifier: Programming Language :: Python :: 3.9
Classifier: Programming Language :: Python :: 3.10
Classifier: Topic :: Scientific/Engineering :: Mathematics
Classifier: Topic :: Software Development :: Libraries
Requires-Dist: torch
Requires-Dist: torchvision
Requires-Dist: torchaudio
Requires-Dist: ttkbootstrap (==0.5.1)
Requires-Dist: pytorchsummary
Requires-Dist: sklearn
Requires-Dist: pandas
Requires-Dist: dask
Requires-Dist: dask-ml
Requires-Dist: tqdm
Requires-Dist: psutil
Requires-Dist: matplotlib
Requires-Dist: tensorflow-gpu (==2.8.0)
Requires-Dist: protobuf (==3.19.0)
